daily_reporter/__init__.py
daily_reporter/main.py
daily_reporter-0.1.0.dist-info/METADATA
daily_reporter-0.1.0.dist-info/WHEEL
daily_reporter-0.1.0.dist-info/entry_points.txt
daily_reporter-0.1.0.dist-info/RECORD
