Metadata-Version: 2.3
Name: daily-reporter
Version: 0.1.0
Summary: 
Author: amin masoudi
Author-email: aminmasoudi2003@gmail.com
Requires-Python: >=3.13
Classifier: Programming Language :: Python :: 3
Classifier: Programming Language :: Python :: 3.13
Requires-Dist: click (>=8.3.1,<9.0.0)
Requires-Dist: jdatetime (>=5.2.0,<6.0.0)
